pipefunc/__init__.py
pipefunc/_adaptive.py
pipefunc/_error_handling.py
pipefunc/_pipefunc.py
pipefunc/_pipefunc_utils.py
pipefunc/_plotting.py
pipefunc/_plotting_utils.py
pipefunc/_profile.py
pipefunc/_utils.py
pipefunc/_variant_pipeline.py
pipefunc/_version.py
pipefunc/cache.py
pipefunc/exceptions.py
pipefunc/helpers.py
pipefunc/lazy.py
pipefunc/mcp.py
pipefunc/py.typed
pipefunc/resources.py
pipefunc/sweep.py
pipefunc/testing.py
pipefunc/typing.py
pipefunc/_pipeline/__init__.py
pipefunc/_pipeline/_autodoc.py
pipefunc/_pipeline/_base.py
pipefunc/_pipeline/_cache.py
pipefunc/_pipeline/_cli.py
pipefunc/_pipeline/_mapspec.py
pipefunc/_pipeline/_pydantic.py
pipefunc/_pipeline/_simplify.py
pipefunc/_pipeline/_types.py
pipefunc/_pipeline/_validation.py
pipefunc/_widgets/__init__.py
pipefunc/_widgets/async_status_widget.py
pipefunc/_widgets/helpers.py
pipefunc/_widgets/output_tabs.py
pipefunc/_widgets/progress_base.py
pipefunc/_widgets/progress_headless.py
pipefunc/_widgets/progress_ipywidgets.py
pipefunc/_widgets/progress_rich.py
pipefunc/map/LICENSE
pipefunc/map/__init__.py
pipefunc/map/_adaptive_scheduler_slurm_executor.py
pipefunc/map/_load.py
pipefunc/map/_mapspec.py
pipefunc/map/_prepare.py
pipefunc/map/_progress.py
pipefunc/map/_result.py
pipefunc/map/_run.py
pipefunc/map/_run_eager.py
pipefunc/map/_run_eager_async.py
pipefunc/map/_run_info.py
pipefunc/map/_shapes.py
pipefunc/map/_types.py
pipefunc/map/adaptive.py
pipefunc/map/adaptive_scheduler.py
pipefunc/map/xarray.py
pipefunc/map/_storage_array/__init__.py
pipefunc/map/_storage_array/_base.py
pipefunc/map/_storage_array/_dict.py
pipefunc/map/_storage_array/_file.py
pipefunc/map/_storage_array/_zarr.py
pipefunc-0.90.2.dist-info/METADATA
pipefunc-0.90.2.dist-info/WHEEL
pipefunc-0.90.2.dist-info/licenses/AUTHORS.md
pipefunc-0.90.2.dist-info/licenses/LICENSE
pipefunc-0.90.2.dist-info/RECORD
