Metadata-Version: 2.4
Name: pipefunc
Version: 0.90.2
Summary: A Python library for defining, managing, and executing function pipelines.
Project-URL: homepage, https://pipefunc.readthedocs.io/
Project-URL: documentation, https://pipefunc.readthedocs.io/
Project-URL: repository, https://github.com/pipefunc/pipefunc
Maintainer-email: Bas Nijholt <bas@nijho.lt>
License: MIT
License-File: AUTHORS.md
License-File: LICENSE
Classifier: Development Status :: 4 - Beta
Classifier: Intended Audience :: Developers
Classifier: Intended Audience :: Science/Research
Classifier: License :: OSI Approved :: MIT License
Classifier: Operating System :: OS Independent
Classifier: Programming Language :: Python
Classifier: Programming Language :: Python :: 3
Classifier: Programming Language :: Python :: 3.11
Classifier: Programming Language :: Python :: 3.12
Classifier: Programming Language :: Python :: 3.13
Classifier: Programming Language :: Python :: 3.14
Classifier: Topic :: Scientific/Engineering
Classifier: Topic :: System :: Distributed Computing
Requires-Python: >=3.11
Requires-Dist: cloudpickle
Requires-Dist: networkx
Requires-Dist: numpy
Provides-Extra: adaptive
Requires-Dist: adaptive; extra == 'adaptive'
Requires-Dist: adaptive-scheduler>=2.14.0; extra == 'adaptive'
Provides-Extra: all
Requires-Dist: adaptive; extra == 'all'
Requires-Dist: adaptive-scheduler>=2.14.0; extra == 'all'
Requires-Dist: bokeh; extra == 'all'
Requires-Dist: fastmcp>=2.12.0; extra == 'all'
Requires-Dist: graphviz; extra == 'all'
Requires-Dist: graphviz-anywidget>=0.7.0; extra == 'all'
Requires-Dist: griffe; extra == 'all'
Requires-Dist: holoviews>=1.14.0; extra == 'all'
Requires-Dist: ipywidgets; extra == 'all'
Requires-Dist: matplotlib; extra == 'all'
Requires-Dist: numcodecs; extra == 'all'
Requires-Dist: pandas; extra == 'all'
Requires-Dist: polars; extra == 'all'
Requires-Dist: psutil; extra == 'all'
Requires-Dist: pydantic; extra == 'all'
Requires-Dist: rich; extra == 'all'
Requires-Dist: rich-argparse; extra == 'all'
Requires-Dist: xarray; extra == 'all'
Requires-Dist: zarr>=3; extra == 'all'
Provides-Extra: autodoc
Requires-Dist: griffe; extra == 'autodoc'
Requires-Dist: rich; extra == 'autodoc'
Provides-Extra: cli
Requires-Dist: griffe; extra == 'cli'
Requires-Dist: pydantic; extra == 'cli'
Requires-Dist: rich; extra == 'cli'
Requires-Dist: rich-argparse; extra == 'cli'
Provides-Extra: dev
Requires-Dist: adaptive; extra == 'dev'
Requires-Dist: adaptive-scheduler>=2.14.0; extra == 'dev'
Requires-Dist: black[jupyter]; extra == 'dev'
Requires-Dist: bokeh; extra == 'dev'
Requires-Dist: cffi<2.0.0; extra == 'dev'
Requires-Dist: coverage; extra == 'dev'
Requires-Dist: emoji; extra == 'dev'
Requires-Dist: fastmcp>=2.12.0; extra == 'dev'
Requires-Dist: graphviz; extra == 'dev'
Requires-Dist: graphviz-anywidget>=0.7.0; extra == 'dev'
Requires-Dist: griffe; extra == 'dev'
Requires-Dist: holoviews>=1.14.0; extra == 'dev'
Requires-Dist: ipywidgets; extra == 'dev'
Requires-Dist: jupytext; extra == 'dev'
Requires-Dist: matplotlib; extra == 'dev'
Requires-Dist: mypy; extra == 'dev'
Requires-Dist: myst-nb; extra == 'dev'
Requires-Dist: myst-parser; extra == 'dev'
Requires-Dist: nltk; extra == 'dev'
Requires-Dist: numcodecs; extra == 'dev'
Requires-Dist: pandas; extra == 'dev'
Requires-Dist: polars; extra == 'dev'
Requires-Dist: pre-commit; extra == 'dev'
Requires-Dist: pre-commit-uv; extra == 'dev'
Requires-Dist: psutil; extra == 'dev'
Requires-Dist: pydantic; extra == 'dev'
Requires-Dist: pytest; extra == 'dev'
Requires-Dist: pytest-asyncio; extra == 'dev'
Requires-Dist: pytest-codspeed; extra == 'dev'
Requires-Dist: pytest-cov; extra == 'dev'
Requires-Dist: pytest-timeout; extra == 'dev'
Requires-Dist: pytest-xdist; extra == 'dev'
Requires-Dist: rich; extra == 'dev'
Requires-Dist: rich-argparse; extra == 'dev'
Requires-Dist: ruff; extra == 'dev'
Requires-Dist: scikit-image; extra == 'dev'
Requires-Dist: seaborn; extra == 'dev'
Requires-Dist: sphinx; extra == 'dev'
Requires-Dist: sphinx-autodoc-typehints; extra == 'dev'
Requires-Dist: sphinx-book-theme; extra == 'dev'
Requires-Dist: sphinx-copybutton; extra == 'dev'
Requires-Dist: sphinx-llms-txt; extra == 'dev'
Requires-Dist: sphinx-notfound-page; extra == 'dev'
Requires-Dist: sphinx-togglebutton; extra == 'dev'
Requires-Dist: sphinxcontrib-mermaid; extra == 'dev'
Requires-Dist: versioningit; extra == 'dev'
Requires-Dist: xarray; extra == 'dev'
Requires-Dist: zarr>=3; extra == 'dev'
Provides-Extra: docs
Requires-Dist: adaptive; extra == 'docs'
Requires-Dist: adaptive-scheduler>=2.14.0; extra == 'docs'
Requires-Dist: bokeh; extra == 'docs'
Requires-Dist: emoji; extra == 'docs'
Requires-Dist: fastmcp>=2.12.0; extra == 'docs'
Requires-Dist: graphviz; extra == 'docs'
Requires-Dist: graphviz-anywidget>=0.7.0; extra == 'docs'
Requires-Dist: griffe; extra == 'docs'
Requires-Dist: holoviews>=1.14.0; extra == 'docs'
Requires-Dist: ipywidgets; extra == 'docs'
Requires-Dist: jupytext; extra == 'docs'
Requires-Dist: matplotlib; extra == 'docs'
Requires-Dist: myst-nb; extra == 'docs'
Requires-Dist: myst-parser; extra == 'docs'
Requires-Dist: nltk; extra == 'docs'
Requires-Dist: numcodecs; extra == 'docs'
Requires-Dist: pandas; extra == 'docs'
Requires-Dist: polars; extra == 'docs'
Requires-Dist: psutil; extra == 'docs'
Requires-Dist: pydantic; extra == 'docs'
Requires-Dist: rich; extra == 'docs'
Requires-Dist: rich-argparse; extra == 'docs'
Requires-Dist: scikit-image; extra == 'docs'
Requires-Dist: seaborn; extra == 'docs'
Requires-Dist: sphinx; extra == 'docs'
Requires-Dist: sphinx-autodoc-typehints; extra == 'docs'
Requires-Dist: sphinx-book-theme; extra == 'docs'
Requires-Dist: sphinx-copybutton; extra == 'docs'
Requires-Dist: sphinx-llms-txt; extra == 'docs'
Requires-Dist: sphinx-notfound-page; extra == 'docs'
Requires-Dist: sphinx-togglebutton; extra == 'docs'
Requires-Dist: sphinxcontrib-mermaid; extra == 'docs'
Requires-Dist: versioningit; extra == 'docs'
Requires-Dist: xarray; extra == 'docs'
Requires-Dist: zarr>=3; extra == 'docs'
Provides-Extra: extras
Requires-Dist: adaptive; extra == 'extras'
Requires-Dist: graphviz; extra == 'extras'
Requires-Dist: graphviz-anywidget; extra == 'extras'
Requires-Dist: griffe; extra == 'extras'
Requires-Dist: ipywidgets; extra == 'extras'
Requires-Dist: matplotlib; extra == 'extras'
Requires-Dist: pandas; extra == 'extras'
Requires-Dist: polars; extra == 'extras'
Requires-Dist: psutil; extra == 'extras'
Requires-Dist: pydantic; extra == 'extras'
Requires-Dist: rich; extra == 'extras'
Requires-Dist: rich-argparse; extra == 'extras'
Requires-Dist: xarray; extra == 'extras'
Requires-Dist: zarr>=3; extra == 'extras'
Provides-Extra: mcp
Requires-Dist: fastmcp>=2.12.0; extra == 'mcp'
Requires-Dist: griffe; extra == 'mcp'
Requires-Dist: rich; extra == 'mcp'
Provides-Extra: pandas
Requires-Dist: pandas; extra == 'pandas'
Requires-Dist: xarray; extra == 'pandas'
Provides-Extra: plotting
Requires-Dist: bokeh; extra == 'plotting'
Requires-Dist: graphviz; extra == 'plotting'
Requires-Dist: holoviews>=1.14.0; extra == 'plotting'
Requires-Dist: matplotlib; extra == 'plotting'
Provides-Extra: polars
Requires-Dist: pandas; extra == 'polars'
Requires-Dist: polars; extra == 'polars'
Requires-Dist: xarray; extra == 'polars'
Provides-Extra: profiling
Requires-Dist: psutil; extra == 'profiling'
Provides-Extra: pydantic
Requires-Dist: pydantic; extra == 'pydantic'
Provides-Extra: rich
Requires-Dist: rich; extra == 'rich'
Provides-Extra: test
Requires-Dist: cffi<2.0.0; extra == 'test'
Requires-Dist: coverage; extra == 'test'
Requires-Dist: pytest; extra == 'test'
Requires-Dist: pytest-asyncio; extra == 'test'
Requires-Dist: pytest-codspeed; extra == 'test'
Requires-Dist: pytest-cov; extra == 'test'
Requires-Dist: pytest-timeout; extra == 'test'
Requires-Dist: pytest-xdist; extra == 'test'
Requires-Dist: versioningit; extra == 'test'
Provides-Extra: widgets
Requires-Dist: graphviz-anywidget>=0.7.0; extra == 'widgets'
Requires-Dist: ipywidgets; extra == 'widgets'
Provides-Extra: xarray
Requires-Dist: xarray; extra == 'xarray'
Provides-Extra: zarr
Requires-Dist: numcodecs; extra == 'zarr'
Requires-Dist: zarr>=3; extra == 'zarr'
